scippuncertainty/__init__.py
scippuncertainty/_progress.py
scippuncertainty/_util.py
scippuncertainty/correlation.py
scippuncertainty/logging.py
scippuncertainty/py.typed
scippuncertainty/random.py
scippuncertainty/mc/__init__.py
scippuncertainty/mc/accumulator.py
scippuncertainty/mc/driver.py
scippuncertainty/mc/sampler.py
scippuncertainty-24.5.0.dist-info/LICENSE
scippuncertainty-24.5.0.dist-info/METADATA
scippuncertainty-24.5.0.dist-info/WHEEL
scippuncertainty-24.5.0.dist-info/top_level.txt
scippuncertainty-24.5.0.dist-info/RECORD
