Metadata-Version: 2.1
Name: scippuncertainty
Version: 24.5.0
Summary: Advanced uncertainty propagation with Scipp
Author: Scipp contributors
License: BSD 3-Clause License
Project-URL: Bug Tracker, https://github.com/scipp/scippuncertainty/issues
Project-URL: Documentation, https://scipp.github.io/scippuncertainty
Project-URL: Source, https://github.com/scipp/scippuncertainty
Classifier: Intended Audience :: Science/Research
Classifier: License :: OSI Approved :: BSD License
Classifier: Natural Language :: English
Classifier: Operating System :: OS Independent
Classifier: Programming Language :: Python :: 3
Classifier: Programming Language :: Python :: 3 :: Only
Classifier: Programming Language :: Python :: 3.10
Classifier: Programming Language :: Python :: 3.11
Classifier: Programming Language :: Python :: 3.12
Classifier: Topic :: Scientific/Engineering
Classifier: Typing :: Typed
Requires-Python: >=3.10
License-File: LICENSE
Requires-Dist: scipp
Provides-Extra: all
Requires-Dist: rich ; extra == 'all'
